xcapi/__init__.py
xcapi/constant/__init__.py
xcapi/model/__init__.py
xcapi/utils/__init__.py
xcapi/utils/xrayn/__init__.py
xcapi/xray/__init__.py
xcapi/xray/app/__init__.py
xcapi/xray/app/commander/__init__.py
xcapi/xray/app/commander/config.proto
xcapi/xray/app/commander/config_pb.py
xcapi/xray/app/dispatcher/__init__.py
xcapi/xray/app/dispatcher/config.proto
xcapi/xray/app/dispatcher/config_pb.py
xcapi/xray/app/dns/__init__.py
xcapi/xray/app/dns/config.proto
xcapi/xray/app/dns/config_pb.py
xcapi/xray/app/dns/fakedns/__init__.py
xcapi/xray/app/dns/fakedns/fakedns.proto
xcapi/xray/app/dns/fakedns/fakedns_pb.py
xcapi/xray/app/log/__init__.py
xcapi/xray/app/log/command/__init__.py
xcapi/xray/app/log/command/config.proto
xcapi/xray/app/log/command/config_grpc_pb.py
xcapi/xray/app/log/command/config_pb.py
xcapi/xray/app/log/config.proto
xcapi/xray/app/log/config_pb.py
xcapi/xray/app/metrics/__init__.py
xcapi/xray/app/metrics/config.proto
xcapi/xray/app/metrics/config_pb.py
xcapi/xray/app/observatory/__init__.py
xcapi/xray/app/observatory/burst/__init__.py
xcapi/xray/app/observatory/burst/config.proto
xcapi/xray/app/observatory/burst/config_pb.py
xcapi/xray/app/observatory/command/__init__.py
xcapi/xray/app/observatory/command/command.proto
xcapi/xray/app/observatory/command/command_grpc_pb.py
xcapi/xray/app/observatory/command/command_pb.py
xcapi/xray/app/observatory/config.proto
xcapi/xray/app/observatory/config_pb.py
xcapi/xray/app/policy/__init__.py
xcapi/xray/app/policy/config.proto
xcapi/xray/app/policy/config_pb.py
xcapi/xray/app/proxyman/__init__.py
xcapi/xray/app/proxyman/command/__init__.py
xcapi/xray/app/proxyman/command/command.proto
xcapi/xray/app/proxyman/command/command_grpc_pb.py
xcapi/xray/app/proxyman/command/command_pb.py
xcapi/xray/app/proxyman/config.proto
xcapi/xray/app/proxyman/config_pb.py
xcapi/xray/app/reverse/__init__.py
xcapi/xray/app/reverse/config.proto
xcapi/xray/app/reverse/config_pb.py
xcapi/xray/app/router/__init__.py
xcapi-24.11.21.dist-info/LICENSE
xcapi-24.11.21.dist-info/METADATA
xcapi-24.11.21.dist-info/WHEEL
xcapi-24.11.21.dist-info/RECORD
