Metadata-Version: 2.1
Name: xcapi
Version: 24.11.21
Summary: Python library for communicating with the xray grpc api
Home-page: https://github.com/Acer-Platanoides/xcapi
License: MIT
Author: AcerPlatanoides.L
Author-email: AcerPlatanoides.L@proton.me
Requires-Python: >=3.9,<4.0
Classifier: License :: OSI Approved :: MIT License
Classifier: Programming Language :: Python :: 3
Classifier: Programming Language :: Python :: 3.9
Classifier: Programming Language :: Python :: 3.10
Classifier: Programming Language :: Python :: 3.11
Classifier: Programming Language :: Python :: 3.12
Requires-Dist: grpcio (>=1.66.2,<2.0.0)
Requires-Dist: grpcio-tools (>=1.66.2,<2.0.0)
Requires-Dist: pydantic (>=2.10.2,<3.0.0)
Project-URL: Repository, https://github.com/Acer-Platanoides/xcapi
